scalr_manage
