Metadata-Version: 1.0
Name: scalr-manage
Version: 7.11.0
Summary: Management CLI for the Scalr installer
Home-page: https://github.com/scalr/installer-ng
Author: Thomas Orozco
Author-email: thomas@scalr.com
License: Apache Software License 2.0
Platform: UNKNOWN
